kikyo/__init__.py
kikyo/client.py
kikyo/config.py
kikyo/datahub.py
kikyo/oss.py
kikyo/search.py
kikyo/settings.py
kikyo/bundle/__init__.py
kikyo/bundle/config.py
kikyo/bundle/datahub.py
kikyo/bundle/oss.py
kikyo/bundle/search.py
kikyo-0.13.14.dist-info/licenses/LICENSE
kikyo-0.13.14.dist-info/METADATA
kikyo-0.13.14.dist-info/WHEEL
kikyo-0.13.14.dist-info/entry_points.txt
kikyo-0.13.14.dist-info/top_level.txt
kikyo-0.13.14.dist-info/RECORD
