Metadata-Version: 2.4
Name: kikyo
Version: 0.13.14
Summary: kikyo package
Author: jadbin
Author-email: jadbin.com@hotmail.com
License: MIT
Classifier: License :: OSI Approved :: MIT License
Classifier: Intended Audience :: Developers
Classifier: Programming Language :: Python
Classifier: Programming Language :: Python :: 3
Classifier: Topic :: Software Development :: Libraries :: Python Modules
Requires-Python: >=3.7
License-File: LICENSE
Requires-Dist: PyYAML>=5.4.1
Requires-Dist: requests>=2.25.1
Requires-Dist: pulsar-client<3,>=2.7.0
Requires-Dist: minio<8.0,>=7.0.1
Requires-Dist: elasticsearch<7.14,>=7.13.1
Requires-Dist: oss2>=2.14.0
Requires-Dist: fastavro>=0.24.0
Requires-Dist: pydantic>=1.8.1
Requires-Dist: numpy<2
Requires-Dist: importlib-metadata
Dynamic: author
Dynamic: author-email
Dynamic: classifier
Dynamic: description
Dynamic: license
Dynamic: license-file
Dynamic: requires-dist
Dynamic: requires-python
Dynamic: summary
